lazycommit/__init__.py
lazycommit/cache.py
lazycommit/cli.py
lazycommit/config.py
lazycommit/core.py
lazycommit/detector.py
lazycommit/errors.py
lazycommit/exceptions.py
lazycommit/generator.py
lazycommit/git_state.py
lazycommit/monitor.py
lazycommit/prompts.py
lazycommit/retry.py
lazycommit_cli-0.2.0.dist-info/METADATA
lazycommit_cli-0.2.0.dist-info/WHEEL
lazycommit_cli-0.2.0.dist-info/entry_points.txt
lazycommit_cli-0.2.0.dist-info/licenses/LICENSE
lazycommit_cli-0.2.0.dist-info/RECORD
