Metadata-Version: 2.4
Name: lazycommit-cli
Version: 0.2.0
Summary: Automatic git commit and push tool with LLM-generated commit messages
Project-URL: Homepage, https://github.com/nrmlthms/lazycommit
Project-URL: Repository, https://github.com/nrmlthms/lazycommit
Project-URL: Issues, https://github.com/nrmlthms/lazycommit/issues
Author-email: nrmlthms <nrmlthms@users.noreply.github.com>
License: MIT
License-File: LICENSE
Keywords: automation,cli,commit,git,llm,openai
Classifier: Development Status :: 3 - Alpha
Classifier: Intended Audience :: Developers
Classifier: License :: OSI Approved :: MIT License
Classifier: Programming Language :: Python :: 3
Classifier: Programming Language :: Python :: 3.12
Classifier: Programming Language :: Python :: 3.13
Classifier: Topic :: Software Development :: Version Control :: Git
Classifier: Topic :: Utilities
Requires-Python: >=3.12
Requires-Dist: openai>=1.0.0
Requires-Dist: rich>=13.0.0
Requires-Dist: typer>=0.9.0
Provides-Extra: monitor
Requires-Dist: watchfiles>=0.21.0; extra == 'monitor'
